phrasedml/__init__.py
phrasedml/libphrasedml.dll
phrasedml/phrasedml.py
phrasedml-1.3.0.dist-info/METADATA
phrasedml-1.3.0.dist-info/WHEEL
phrasedml-1.3.0.dist-info/top_level.txt
phrasedml-1.3.0.dist-info/RECORD
