Metadata-Version: 2.1
Name: phrasedml
Version: 1.3.0
Summary: Python bindings for phraSED-ML
Home-page: https://github.com/sys-bio/phrasedml
Author: Lucian Smith, Kiri Choi, J Kyle Medley, and Herbert Sauro
Author-email: lpsmith@uw.edu
License: MIT
